tedit/__init__.py
tedit/__main__.py
tedit/_pip_only.py
tedit/app.py
tedit-0.9.1.dist-info/licenses/LICENSE.txt
tedit-0.9.1.dist-info/licenses/licenses/LICENSE_BSD.txt
tedit-0.9.1.dist-info/licenses/licenses/LICENSE_PSF.txt
tedit-0.9.1.dist-info/METADATA
tedit-0.9.1.dist-info/WHEEL
tedit-0.9.1.dist-info/entry_points.txt
tedit-0.9.1.dist-info/top_level.txt
tedit-0.9.1.dist-info/RECORD
